Metadata-Version: 1.1
Name: clowder
Version: 0.1.5
Summary: Client for the Clowder monitoring server
Home-page: https://github.com/keithhackbarth/clowder_client
Author: Keith Hackbarth
Author-email: keith@clowder.io
License: LICENCE.txt
Download-URL: https://github.com/keithhackbarth/clowder_client/archive/master.zip
Keywords: clowder
Platform: Cross-platform
Classifier: Programming Language :: Python
Classifier: Programming Language :: Python :: 3
Classifier: Programming Language :: Python :: 2.7
